defspec-0.5.0.dist-info/METADATA
defspec-0.5.0.dist-info/WHEEL
defspec-0.5.0.dist-info/entry_points.txt
defspec-0.5.0.dist-info/licenses/LICENSE
defspec/__init__.py
defspec/__version__.py
defspec/py.typed
defspec/server.py
defspec/spec.py
defspec/template.py
defspec-0.5.0.dist-info/RECORD
