Metadata-Version: 2.1
Name: defspec
Version: 0.5.0
Summary: OpenAPI spec generation and web page rendering.
Author-Email: Keming <kemingy94@gmail.com>
License: Apache-2.0
Classifier: Intended Audience :: Developers
Classifier: Programming Language :: Python :: 3.9
Classifier: Programming Language :: Python :: 3.10
Classifier: Programming Language :: Python :: 3.11
Classifier: Programming Language :: Python :: 3.12
Classifier: Programming Language :: Python :: 3.13
Project-URL: Homepage, https://github.com/kemingy/defspec
Requires-Python: >=3.9
Requires-Dist: msgspec>=0.19.0
Requires-Dist: typing-extensions~=4.9; python_full_version < "3.11"
Provides-Extra: offline
Requires-Dist: offapi>=0.1.1; extra == "offline"
